earcutx.cp39-win32.pyd
earcutx-1.0.4.dist-info/LICENSE.md
earcutx-1.0.4.dist-info/METADATA
earcutx-1.0.4.dist-info/WHEEL
earcutx-1.0.4.dist-info/top_level.txt
earcutx-1.0.4.dist-info/RECORD
