Metadata-Version: 2.1
Name: earcutx
Version: 1.0.4
Summary: Python bindings for the mapbox earcut C++ polygon triangulation library.
Author-email: Samuel Kogler <samuel.kogler@gmail.com>
License: The bindings to the earcut library are licensed under the following terms:
Project-URL: Source, https://github.com/skogler/mapbox_earcut_python
Project-URL: CSource, https://github.com/mapbox/earcut.hpp
Requires-Python: >=3.8
License-File: LICENSE.md
Requires-Dist: numpy >=1.24.0
Provides-Extra: test
Requires-Dist: pytest ; extra == 'test'
